setup.py
blitzdb/__init__.py
blitzdb/document.py
blitzdb/helpers.py
blitzdb/queryset.py
blitzdb.egg-info/PKG-INFO
blitzdb.egg-info/SOURCES.txt
blitzdb.egg-info/dependency_links.txt
blitzdb.egg-info/not-zip-safe
blitzdb.egg-info/requires.txt
blitzdb.egg-info/top_level.txt
blitzdb/backends/__init__.py
blitzdb/backends/base.py
blitzdb/backends/file/__init__.py
blitzdb/backends/file/backend.py
blitzdb/backends/file/index.py
blitzdb/backends/file/queries.py
blitzdb/backends/file/queryset.py
blitzdb/backends/file/serializers.py
blitzdb/backends/file/store.py
blitzdb/backends/file/utils.py
blitzdb/backends/mongo/__init__.py
blitzdb/backends/mongo/backend.py
blitzdb/backends/mongo/queryset.py
blitzdb/backends/sql/__init__.py
blitzdb/backends/sql/backend.py
blitzdb/backends/sql/queryset.py
blitzdb/backends/sql/relations.py
blitzdb/fields/__init__.py
blitzdb/fields/base.py
blitzdb/fields/binary.py
blitzdb/fields/boolean.py
blitzdb/fields/char.py
blitzdb/fields/date.py
blitzdb/fields/datetime.py
blitzdb/fields/email.py
blitzdb/fields/enum.py
blitzdb/fields/float.py
blitzdb/fields/foreignkey.py
blitzdb/fields/integer.py
blitzdb/fields/manytomany.py
blitzdb/fields/onetomany.py
blitzdb/fields/text.py
blitzdb/tests/__init__.py
blitzdb/tests/fixtures.py
blitzdb/tests/test_array_queries.py
blitzdb/tests/test_autoload.py
blitzdb/tests/test_dbref_includes.py
blitzdb/tests/test_documents.py
blitzdb/tests/test_encoding.py
blitzdb/tests/test_exceptions.py
blitzdb/tests/test_file_stores.py
blitzdb/tests/test_get.py
blitzdb/tests/test_hooks.py
blitzdb/tests/test_query_operators.py
blitzdb/tests/test_querying.py
blitzdb/tests/test_relations.py
blitzdb/tests/test_serialization.py
blitzdb/tests/test_sorting.py
blitzdb/tests/test_transactions.py
blitzdb/tests/test_update.py
blitzdb/tests/file/__init__.py
blitzdb/tests/file/test_unique_index.py
blitzdb/tests/helpers/__init__.py
blitzdb/tests/helpers/movie_data.py
blitzdb/tests/mongo/__init__.py
blitzdb/tests/mongo/test_complex.py
blitzdb/tests/mongo/test_dots.py
blitzdb/tests/mongo/test_regex.py
blitzdb/tests/mongo/test_update.py
blitzdb/tests/sql/__init__.py
blitzdb/tests/sql/fixtures.py
blitzdb/tests/sql/test_backrefs.py
