Metadata-Version: 1.0
Name: blitzdb
Version: 0.4.4
Summary: A document-oriented database written purely in Python.
Home-page: https://github.com/adewes/blitzdb
Author: Andreas Dewes - 7scientists
Author-email: andreas@7scientists.com
License: MIT
Platform: UNKNOWN
